InSpice/__init__.py
InSpice/Cache/__init__.py
InSpice/Config/ConfigInstall.py
InSpice/Config/__init__.py
InSpice/Config/logging.yml
InSpice/DeviceLibrary/__init__.py
InSpice/Doc/ExampleTools.py
InSpice/Doc/__init__.py
InSpice/Export/Hdf5.py
InSpice/Export/__init__.py
InSpice/KiCad/__init__.py
InSpice/Logging/Logging.py
InSpice/Logging/__init__.py
InSpice/Math/Calculus.py
InSpice/Math/__init__.py
InSpice/Physics/MaterialProperties.py
InSpice/Physics/PhysicalConstants.py
InSpice/Physics/Resistor.py
InSpice/Physics/SemiConductor.py
InSpice/Physics/__init__.py
InSpice/Plot/BodeDiagram.py
InSpice/Plot/__init__.py
InSpice/Probe/Plot.py
InSpice/Probe/WaveForm.py
InSpice/Probe/__init__.py
InSpice/Scripts/Library.py
InSpice/Scripts/__init__.py
InSpice/Scripts/cir2py.py
InSpice/Scripts/inspice_post_installation.py
InSpice/Scripts/pyspice_post_installation.py
InSpice/Spice/AnalysisParameters.py
InSpice/Spice/BasicElement.py
InSpice/Spice/DeviceModel.py
InSpice/Spice/Element.py
InSpice/Spice/ElementParameter.py
InSpice/Spice/FakeDipole.py
InSpice/Spice/HighLevelElement.py
InSpice/Spice/Netlist.py
InSpice/Spice/RawFile.py
InSpice/Spice/Simulation.py
InSpice/Spice/Simulator.py
InSpice/Spice/StringTools.py
InSpice/Spice/__init__.py
InSpice/Spice/unit.py
InSpice/Spice/Library/Library.py
InSpice/Spice/Library/SpiceInclude.py
InSpice/Spice/Library/__init__.py
InSpice/Spice/Library/product-categories/digi-key.yaml
InSpice/Spice/Library/product-categories/infineon.yaml
InSpice/Spice/Library/product-categories/mouser.yaml
InSpice/Spice/NgSpice/ManualExampleExtractor.py
InSpice/Spice/NgSpice/ManualExamples.py
InSpice/Spice/NgSpice/RawFile.py
InSpice/Spice/NgSpice/Server.py
InSpice/Spice/NgSpice/Shared.py
InSpice/Spice/NgSpice/SimulationType.py
InSpice/Spice/NgSpice/Simulator.py
InSpice/Spice/NgSpice/__init__.py
InSpice/Spice/NgSpice/api.h
InSpice/Spice/Parser/Ast.py
InSpice/Spice/Parser/ElementData.py
InSpice/Spice/Parser/HighLevelParser.py
InSpice/Spice/Parser/Parser.py
inspice-1.6.4.4.dist-info/licenses/LICENSE.txt
inspice-1.6.4.4.dist-info/METADATA
inspice-1.6.4.4.dist-info/WHEEL
inspice-1.6.4.4.dist-info/entry_points.txt
inspice-1.6.4.4.dist-info/top_level.txt
inspice-1.6.4.4.dist-info/RECORD
