Metadata-Version: 2.4
Name: InSpice
Version: 1.6.4.4
Summary: Python interface to Ngspice and Xyce circuit simulators (forked from InSpice)
Author-email: Innovoltive <info@innovoltive.com>
License: GPL-3.0-or-later
Project-URL: Homepage, https://github.com/Innovoltive/InSpice
Project-URL: Bug Tracker, https://github.com/Innovoltive/InSpice/issues
Classifier: Development Status :: 4 - Beta
Classifier: Programming Language :: Python :: 3
Classifier: Programming Language :: Python :: 3.12
Classifier: License :: OSI Approved :: GNU General Public License v3 (GPLv3)
Classifier: Operating System :: OS Independent
Classifier: Topic :: Scientific/Engineering :: Electronic Design Automation (EDA)
Classifier: Topic :: Scientific/Engineering :: Physics
Requires-Python: >=3.12
License-File: LICENSE.txt
Requires-Dist: numpy
Requires-Dist: matplotlib
Requires-Dist: PyYAML
Requires-Dist: cffi>=1.0.0
Requires-Dist: diskcache
Requires-Dist: h5py
Requires-Dist: ply
Provides-Extra: dev
Requires-Dist: pytest; extra == "dev"
Requires-Dist: twine; extra == "dev"
Requires-Dist: build; extra == "dev"
Requires-Dist: flake8; extra == "dev"
Requires-Dist: scipy; extra == "dev"
Requires-Dist: pint; extra == "dev"
Requires-Dist: KiCadRW; extra == "dev"
Requires-Dist: sexpdata; extra == "dev"
Dynamic: license-file
